{
  "_id": "a25b546bf0e3b71d",
  "name": "Synthacardium",
  "type": "bioware",
  "img": "icons/svg/biohazard.svg",
  "system": {
    "bodySystem": "circulatory",
    "grade": "standard",
    "bodyCost": 0,
    "rating": 1,
    "cost": 0,
    "availability": "",
    "streetIndex": "",
    "legality": "Legal",
    "installed": false,
    "triggered": false,
    "active": false,
    "ratingStats": [
      {
        "rating": 1,
        "bodyCost": 0.2,
        "cost": 6000,
        "availability": "4/10 days",
        "streetIndex": "1.5",
        "armorBallistic": 0,
        "armorImpact": 0
      },
      {
        "rating": 2,
        "bodyCost": 0.3,
        "cost": 15000,
        "availability": "4/10 days",
        "streetIndex": "1.5",
        "armorBallistic": 0,
        "armorImpact": 0
      }
    ],
    "armorBallistic": 0,
    "armorImpact": 0,
    "attributeMods": {
      "body": 0,
      "quickness": 0,
      "strength": 0,
      "charisma": 0,
      "intelligence": 0,
      "willpower": 0,
      "reaction": 0,
      "initiativeDice": 0
    },
    "noReactionBonus": false,
    "activeSkillDice": 0,
    "damageCompensator": false,
    "ignoresStunPenalty": false,
    "notes": "Enhanced myocardium: add Rating dice to Athletics Tests and other sustained-exertion checks (Shadowtech p.16)."
  },
  "effects": [],
  "flags": {},
  "folder": null,
  "sort": 0,
  "_stats": {
    "coreVersion": "13.351",
    "systemId": "sr2e",
    "systemVersion": "0.1.0",
    "createdTime": 1784000000000,
    "modifiedTime": 1784000000000,
    "lastModifiedBy": null,
    "compendiumSource": null,
    "duplicateSource": null,
    "exportSource": null
  },
  "ownership": {
    "default": 0
  },
  "_key": "!items!a25b546bf0e3b71d"
}
